plane_mcp/__init__.py
plane_mcp/__main__.py
plane_mcp/client.py
plane_mcp/server.py
plane_mcp/auth/__init__.py
plane_mcp/auth/plane_header_auth_provider.py
plane_mcp/auth/plane_oauth_provider.py
plane_mcp/tools/__init__.py
plane_mcp/tools/cycles.py
plane_mcp/tools/initiatives.py
plane_mcp/tools/intake.py
plane_mcp/tools/modules.py
plane_mcp/tools/projects.py
plane_mcp/tools/users.py
plane_mcp/tools/work_item_properties.py
plane_mcp/tools/work_items.py
plane_mcp_server-0.2.0.dist-info/licenses/LICENSE
plane_mcp_server-0.2.0.dist-info/METADATA
plane_mcp_server-0.2.0.dist-info/WHEEL
plane_mcp_server-0.2.0.dist-info/entry_points.txt
plane_mcp_server-0.2.0.dist-info/top_level.txt
plane_mcp_server-0.2.0.dist-info/RECORD
