Metadata-Version: 2.4
Name: plane-mcp-server
Version: 0.2.0
Summary: A Model Context Protocol server for Plane integration
Author-email: Surya Prashanth <surya.prashanth@plane.so>, Plane Engineering <support@plane.so>
License: MIT
Keywords: mcp,plane,fastmcp,ai,automation
Requires-Python: >=3.10
License-File: LICENSE
Requires-Dist: fastmcp==2.14.1
Requires-Dist: plane-sdk==0.2.2
Requires-Dist: py-key-value-aio[redis]==0.3.0
Requires-Dist: mcp==1.24.0
Provides-Extra: dev
Requires-Dist: pytest>=7.0.0; extra == "dev"
Requires-Dist: pytest-asyncio>=0.21.0; extra == "dev"
Requires-Dist: black>=23.0.0; extra == "dev"
Requires-Dist: ruff>=0.1.0; extra == "dev"
Dynamic: license-file
